LICENSE
MANIFEST.in
README
README.md
gpl-3.0.txt
setup.py
rocket/0001-fixed-compiler-error.patch
rocket/WebIOPi-0.7.1.bin
rocket/__init__.py
rocket/__main__.py
rocket/webiopi-pi2bplus.patch
rocket/html/Index.html
rocket/modules/DataExchangeBuffer.py
rocket/modules/_DataExchangeBuffer.so
rocket/modules/direction_converter.py
rocket/python/max7219.py
rocket/python/script.py
rocket_pi.egg-info/PKG-INFO
rocket_pi.egg-info/SOURCES.txt
rocket_pi.egg-info/dependency_links.txt
rocket_pi.egg-info/not-zip-safe
rocket_pi.egg-info/top_level.txt
rocketlauncher/Digger_Consumer_App
rocketlauncher/__init__.py
rocketlauncher/hostapd
rocketlauncher/rocket.service
rocketlauncher/rocketlauncher.sh
rocketlauncher/rocketlauncherD.sh