Metadata-Version: 2.1
Name: rocket-pi
Version: 1.1
Summary: Remote open control key enabling technology (Rocket)
Home-page: https://github.com/gulliversoft/rocket
Author: gulliversoft
Author-email: fg7@gulliversoft.com
License: GPL3
Platform: UNKNOWN
Classifier: Intended Audience :: Education
Classifier: Development Status :: 5 - Production/Stable
Classifier: Programming Language :: Python :: 3
Classifier: Operating System :: POSIX :: Linux
Classifier: Topic :: Software Development
Classifier: Topic :: Home Automation
Classifier: Topic :: System :: Hardware
